LICENSE
MANIFEST.in
README.md
setup.cfg
setup.py
nessrest/LICENSE
nessrest/__init__.py
nessrest/__init__.pyc
nessrest/credentials.py
nessrest/credentials.pyc
nessrest/ness6rest.py
nessrest/ness6rest.pyc
nessrest/ness6scan.py
nessrest/ness_rest
nessrest/ness_rest.conf.example
nessrest/ness_test
nessrest/nessus-scan
nessrest.egg-info/PKG-INFO
nessrest.egg-info/SOURCES.txt
nessrest.egg-info/dependency_links.txt
nessrest.egg-info/requires.txt
nessrest.egg-info/top_level.txt