Metadata-Version: 1.1
Name: nessrest
Version: 0.40
Summary: An interface to the Nessus 6 REST API
Home-page: https://github.com/tenable/nessrest
Author: Scott Walsh, Ben Bergman, Matthew Everson, Matthew Woelk, Rich Walchuck
Author-email: research@tenable.com
License: Copyright (c) 2014-2015, Tenable Network Security, Inc.
